llama_index/llms/servam/__init__.py
llama_index/llms/servam/base.py
llama_index_llms_servam-0.2.1.dist-info/METADATA
llama_index_llms_servam-0.2.1.dist-info/WHEEL
llama_index_llms_servam-0.2.1.dist-info/RECORD
