Metadata-Version: 2.4
Name: llama-index-llms-servam
Version: 0.2.1
Summary: llama-index llms servam integration
Author-email: Yash Parmar <yashp3020@gmail.com>
License-Expression: MIT
Requires-Python: <4.0,>=3.9
Requires-Dist: llama-index-llms-openai-like<0.6,>=0.5.0
